README
setup.py
kgit/__init__.py
kgit/enforce.py
kgit/kgit.py
kgit/pre-commit.py
kgit/profiles.py
kgit/purge.py
kgit/workspaces.py
kgit.egg-info/PKG-INFO
kgit.egg-info/SOURCES.txt
kgit.egg-info/dependency_links.txt
kgit.egg-info/entry_points.txt
kgit.egg-info/top_level.txt