Metadata-Version: 1.1
Name: kgit
Version: 1.0.3
Summary: Commonly used git convenience functionality for todays modern developer.
Home-page: https://github.com/kris-nova/kgit
Author: Kris Nova
Author-email: kris@nivenly.com
License: MIT
Keywords: git,config,wrapper,manager
Platform: UNKNOWN
Classifier: Development Status :: 5 - Production/Stable
Classifier: Intended Audience :: Developers
Classifier: Topic :: Software Development
Classifier: License :: OSI Approved :: MIT License
Classifier: Environment :: MacOS X
Classifier: Programming Language :: Python :: 2
Classifier: Programming Language :: Python :: 2.6
Classifier: Programming Language :: Python :: 2.7
